CHANGES.rst
COPYING.txt
MANIFEST.in
README.rst
setup.py
./pyctpp2/_pyctpp2_py2.cpp
./pyctpp2/cengine.cc
./pyctpp2/ctemplate.cc
pyctpp2/__init__.py
pyctpp2/_pyctpp2.pyx
pyctpp2/_pyctpp2_py2.cpp
pyctpp2/_pyctpp2_py3.cpp
pyctpp2/cdt.pxd
pyctpp2/cengine.pxd
pyctpp2/ctemplate.pxd
pyctpp2/error_type.pxd
pyctpp2/libintl.pxd
pyctpp2/string.pxd
pyctpp2/version.py
pyctpp2.egg-info/PKG-INFO
pyctpp2.egg-info/SOURCES.txt
pyctpp2.egg-info/dependency_links.txt
pyctpp2.egg-info/entry_points.txt
pyctpp2.egg-info/top_level.txt
pyctpp2/pyctpp2/cdt_funcs.h
pyctpp2/pyctpp2/cengine.h
pyctpp2/pyctpp2/ctemplate.h
pyctpp2/pyctpp2/error_type.h
tests/data/hello.tmpl
tests/data/io-error.tmpl
tests/data/math_expr.tmpl
tests/data/syntax-error.tmpl