Metadata-Version: 1.1
Name: pyctpp2
Version: 0.12.2
Summary: Python interface to CTPP2 library.
Home-page: http://bitbucket.org/klepa/pyctpp2
Author: Konstantin Lepa
Author-email: konstantin.lepa@gmail.com
License: MIT
Platform: UNKNOWN
Classifier: Development Status :: 4 - Beta
Classifier: Environment :: Web Environment
Classifier: Intended Audience :: Developers
Classifier: License :: OSI Approved :: MIT License
Classifier: Operating System :: POSIX
Classifier: Programming Language :: Cython
Classifier: Programming Language :: Python
Classifier: Programming Language :: Python :: 3
Classifier: Topic :: Internet :: WWW/HTTP :: Dynamic Content
Classifier: Topic :: Text Processing :: Markup :: HTML
Requires: Cython(>=0.14)
